{
  "annotations": {
    "list": [
      {
        "builtIn": 1,
        "datasource": {
          "type": "loki",
          "uid": "Loki"
        },
        "enable": true,
        "expr": "{service_name=~\"$service_name\", service_name!=\"unknown_service\", deployment_environment=\"$env\"} | observed_timestamp=\"$ts\"",
        "filter": {
          "exclude": true,
          "ids": [
            1,
            3
          ]
        },
        "hide": false,
        "iconColor": "rgba(0, 211, 255, 1)",
        "name": "Selected log",
        "queryType": "range",
        "target": {
          "limit": 100,
          "matchAny": false,
          "tags": [],
          "type": "dashboard"
        },
        "type": "dashboard"
      }
    ]
  },
  "editable": true,
  "fiscalYearStartMonth": 0,
  "graphTooltip": 0,
  "id": 0,
  "links": [],
  "panels": [
    {
      "collapsed": false,
      "gridPos": {
        "h": 1,
        "w": 24,
        "x": 0,
        "y": 0
      },
      "id": 16,
      "panels": [],
      "title": "Main",
      "type": "row"
    },
    {
      "datasource": {
        "type": "prometheus",
        "uid": "Prometheus"
      },
      "fieldConfig": {
        "defaults": {
          "color": {
            "mode": "palette-classic"
          },
          "custom": {
            "axisBorderShow": false,
            "axisCenteredZero": false,
            "axisColorMode": "text",
            "axisLabel": "",
            "axisPlacement": "auto",
            "barAlignment": 0,
            "barWidthFactor": 0.6,
            "drawStyle": "line",
            "fillOpacity": 0,
            "gradientMode": "none",
            "hideFrom": {
              "legend": false,
              "tooltip": false,
              "viz": false
            },
            "insertNulls": 60000,
            "lineInterpolation": "smooth",
            "lineStyle": {
              "fill": "solid"
            },
            "lineWidth": 1,
            "pointSize": 5,
            "scaleDistribution": {
              "type": "linear"
            },
            "showPoints": "auto",
            "showValues": false,
            "spanNulls": false,
            "stacking": {
              "group": "A",
              "mode": "none"
            },
            "thresholdsStyle": {
              "mode": "dashed"
            }
          },
          "fieldMinMax": false,
          "mappings": [],
          "max": 100,
          "min": 0,
          "thresholds": {
            "mode": "absolute",
            "steps": [
              {
                "color": "green",
                "value": 0
              },
              {
                "color": "red",
                "value": 100
              }
            ]
          },
          "unit": "percent"
        },
        "overrides": []
      },
      "gridPos": {
        "h": 8,
        "w": 16,
        "x": 0,
        "y": 1
      },
      "id": 7,
      "options": {
        "legend": {
          "calcs": [],
          "displayMode": "list",
          "placement": "bottom",
          "showLegend": true
        },
        "tooltip": {
          "hideZeros": false,
          "mode": "single",
          "sort": "none"
        }
      },
      "pluginVersion": "12.3.1",
      "targets": [
        {
          "datasource": {
            "type": "prometheus",
            "uid": "Prometheus"
          },
          "editorMode": "code",
          "exemplar": false,
          "expr": "100 *\r\n(\r\n  sum by (namespace, pod) (\r\n    container_memory_working_set_bytes{\r\n      namespace=\"$ns\",\r\n      pod=~\"$pod\",\r\n      pod!~\".*-sql.*\",\r\n      container!=\"\",\r\n      container!=\"POD\"\r\n    }\r\n  )\r\n)\r\n/\r\nclamp_min(\r\n  sum by (namespace, pod) (\r\n    kube_pod_container_resource_limits{\r\n      namespace=\"$ns\",\r\n      pod=~\"$pod\",\r\n      resource=\"memory\",\r\n      unit=\"byte\"\r\n    }\r\n  ),\r\n  1\r\n)\r\n* on (namespace, pod) group_left(label_app)\r\n    kube_pod_labels{\r\n      namespace=\"$ns\",\r\n      label_service_name=~\"$service_name\",\r\n      pod=~\"$pod\",\r\n      pod!~\".*-sql.*\"\r\n    }",
          "format": "time_series",
          "hide": false,
          "instant": false,
          "legendFormat": "{{pod}}",
          "range": true,
          "refId": "B"
        }
      ],
      "title": "Memory",
      "type": "timeseries"
    },
    {
      "datasource": {
        "type": "prometheus",
        "uid": "Prometheus"
      },
      "fieldConfig": {
        "defaults": {
          "color": {
            "mode": "palette-classic"
          },
          "custom": {
            "axisBorderShow": false,
            "axisCenteredZero": false,
            "axisColorMode": "text",
            "axisLabel": "",
            "axisPlacement": "auto",
            "barAlignment": 0,
            "barWidthFactor": 0.6,
            "drawStyle": "line",
            "fillOpacity": 0,
            "gradientMode": "none",
            "hideFrom": {
              "legend": false,
              "tooltip": false,
              "viz": false
            },
            "insertNulls": 60000,
            "lineInterpolation": "smooth",
            "lineStyle": {
              "fill": "solid"
            },
            "lineWidth": 1,
            "pointSize": 5,
            "scaleDistribution": {
              "type": "linear"
            },
            "showPoints": "auto",
            "showValues": false,
            "spanNulls": false,
            "stacking": {
              "group": "A",
              "mode": "none"
            },
            "thresholdsStyle": {
              "mode": "off"
            }
          },
          "fieldMinMax": false,
          "mappings": [],
          "thresholds": {
            "mode": "absolute",
            "steps": [
              {
                "color": "green",
                "value": 0
              },
              {
                "color": "red",
                "value": 100
              }
            ]
          },
          "unit": "binBps"
        },
        "overrides": []
      },
      "gridPos": {
        "h": 8,
        "w": 8,
        "x": 16,
        "y": 1
      },
      "id": 6,
      "options": {
        "legend": {
          "calcs": [],
          "displayMode": "list",
          "placement": "bottom",
          "showLegend": true
        },
        "tooltip": {
          "hideZeros": false,
          "mode": "single",
          "sort": "none"
        }
      },
      "pluginVersion": "12.3.1",
      "targets": [
        {
          "datasource": {
            "type": "prometheus",
            "uid": "Prometheus"
          },
          "editorMode": "code",
          "exemplar": false,
          "expr": "sum by (pod) (\r\n    rate(container_network_receive_bytes_total{\r\n        namespace=\"$ns\",\r\n        pod=~\"$pod\", \r\n        container=\"POD\",\r\n        container_label_service_name=~\"$service_name\",\r\n        container_label_service_name=~\"$log_service_name\",\r\n        container_label_environment=~\"$env\",\r\n        interface=\"eth0\"\r\n    }\r\n    [$__rate_interval]\r\n    )\r\n)",
          "format": "time_series",
          "hide": false,
          "instant": false,
          "legendFormat": "{{pod}} (receive)",
          "range": true,
          "refId": "A"
        },
        {
          "datasource": {
            "type": "prometheus",
            "uid": "Prometheus"
          },
          "editorMode": "code",
          "exemplar": false,
          "expr": "sum by (pod) (\r\n    rate(container_network_transmit_bytes_total{\r\n        namespace=\"$ns\",\r\n        pod=~\"$pod\", \r\n        container=\"POD\",\r\n        container_label_service_name=~\"$service_name\",\r\n        container_label_service_name=~\"$log_service_name\",\r\n        container_label_environment=~\"$env\",\r\n        interface=\"eth0\"\r\n    }\r\n    [$__rate_interval]\r\n    )\r\n) * -1",
          "format": "time_series",
          "hide": false,
          "instant": false,
          "legendFormat": "{{pod}} (send)",
          "range": true,
          "refId": "B"
        }
      ],
      "title": "Network",
      "type": "timeseries"
    },
    {
      "datasource": {
        "type": "prometheus",
        "uid": "Prometheus"
      },
      "fieldConfig": {
        "defaults": {
          "color": {
            "mode": "palette-classic"
          },
          "custom": {
            "axisBorderShow": false,
            "axisCenteredZero": false,
            "axisColorMode": "text",
            "axisLabel": "",
            "axisPlacement": "auto",
            "barAlignment": 0,
            "barWidthFactor": 0.6,
            "drawStyle": "line",
            "fillOpacity": 0,
            "gradientMode": "none",
            "hideFrom": {
              "legend": false,
              "tooltip": false,
              "viz": false
            },
            "insertNulls": 60000,
            "lineInterpolation": "smooth",
            "lineStyle": {
              "fill": "solid"
            },
            "lineWidth": 1,
            "pointSize": 5,
            "scaleDistribution": {
              "type": "linear"
            },
            "showPoints": "auto",
            "showValues": false,
            "spanNulls": false,
            "stacking": {
              "group": "A",
              "mode": "none"
            },
            "thresholdsStyle": {
              "mode": "dashed"
            }
          },
          "fieldMinMax": false,
          "mappings": [],
          "max": 100,
          "min": 0,
          "thresholds": {
            "mode": "absolute",
            "steps": [
              {
                "color": "green",
                "value": 0
              },
              {
                "color": "red",
                "value": 100
              }
            ]
          },
          "unit": "percent"
        },
        "overrides": []
      },
      "gridPos": {
        "h": 8,
        "w": 16,
        "x": 0,
        "y": 9
      },
      "id": 8,
      "options": {
        "legend": {
          "calcs": [],
          "displayMode": "list",
          "placement": "bottom",
          "showLegend": true
        },
        "tooltip": {
          "hideZeros": false,
          "mode": "single",
          "sort": "none"
        }
      },
      "pluginVersion": "12.3.1",
      "targets": [
        {
          "datasource": {
            "type": "prometheus",
            "uid": "Prometheus"
          },
          "editorMode": "code",
          "exemplar": false,
          "expr": "100 *\r\n(\r\n  sum by (pod, namespace) (\r\n    rate(\r\n      container_cpu_usage_seconds_total{\r\n        namespace=\"$ns\",\r\n        pod=~\"$pod\",\r\n        pod!~\".*-sql.*\",\r\n        container!=\"\",\r\n        container!=\"POD\"\r\n      }[$__rate_interval]\r\n    )\r\n  )\r\n  * on (pod, namespace)\r\n    group_left(label_service_name)\r\n    kube_pod_labels{\r\n      namespace=\"$ns\",\r\n      label_service_name=~\"$service_name\",\r\n      label_environment=~\"$env\",\r\n      pod=~\"$pod\",\r\n      pod!~\".*-sql.*\"\r\n    }\r\n  /\r\n  ignoring(label_service_name)\r\n  sum by (pod, namespace) (\r\n    kube_pod_container_resource_limits{\r\n      namespace=\"$ns\",\r\n      pod=~\"$pod\",\r\n      pod!~\".*-sql.*\",\r\n      resource=\"cpu\",\r\n      unit=\"core\"\r\n    }\r\n  )\r\n)\r\n",
          "format": "time_series",
          "hide": false,
          "instant": false,
          "legendFormat": "{{pod}} (%)",
          "range": true,
          "refId": "A"
        }
      ],
      "title": "CPU",
      "type": "timeseries"
    },
    {
      "datasource": {
        "type": "prometheus",
        "uid": "Prometheus"
      },
      "fieldConfig": {
        "defaults": {
          "color": {
            "mode": "palette-classic"
          },
          "custom": {
            "axisBorderShow": false,
            "axisCenteredZero": false,
            "axisColorMode": "text",
            "axisLabel": "",
            "axisPlacement": "auto",
            "barAlignment": 0,
            "barWidthFactor": 0.6,
            "drawStyle": "line",
            "fillOpacity": 0,
            "gradientMode": "none",
            "hideFrom": {
              "legend": false,
              "tooltip": false,
              "viz": false
            },
            "insertNulls": 60000,
            "lineInterpolation": "smooth",
            "lineStyle": {
              "fill": "solid"
            },
            "lineWidth": 1,
            "pointSize": 5,
            "scaleDistribution": {
              "type": "linear"
            },
            "showPoints": "auto",
            "showValues": false,
            "spanNulls": false,
            "stacking": {
              "group": "A",
              "mode": "none"
            },
            "thresholdsStyle": {
              "mode": "off"
            }
          },
          "fieldMinMax": false,
          "mappings": [],
          "thresholds": {
            "mode": "absolute",
            "steps": [
              {
                "color": "green",
                "value": 0
              },
              {
                "color": "red",
                "value": 0.8
              }
            ]
          },
          "unit": "binBps"
        },
        "overrides": []
      },
      "gridPos": {
        "h": 8,
        "w": 8,
        "x": 16,
        "y": 9
      },
      "id": 9,
      "options": {
        "legend": {
          "calcs": [],
          "displayMode": "list",
          "placement": "bottom",
          "showLegend": true
        },
        "tooltip": {
          "hideZeros": false,
          "mode": "single",
          "sort": "none"
        }
      },
      "pluginVersion": "12.3.1",
      "targets": [
        {
          "datasource": {
            "type": "prometheus",
            "uid": "Prometheus"
          },
          "editorMode": "code",
          "exemplar": false,
          "expr": "sum by (namespace, pod) (\r\n    rate(container_fs_reads_bytes_total{\r\n        namespace=\"$ns\",\r\n        pod=~\"$pod\",\r\n        container!=\"POD\",\r\n        container!=\"\"\r\n    }\r\n    [$__rate_interval])\r\n)\r\n* on (namespace, pod) \r\n  group_left(label_service_name)\r\n    kube_pod_labels{\r\n      namespace=\"$ns\",\r\n      label_service_name=~\"$service_name\",\r\n      label_service_name=~\"$log_service_name\",\r\n      label_environment=~\"$env\",\r\n      pod=~\"$pod\"\r\n    }",
          "format": "time_series",
          "hide": false,
          "instant": false,
          "legendFormat": "{{pod}} (read)",
          "range": true,
          "refId": "A"
        },
        {
          "datasource": {
            "type": "prometheus",
            "uid": "Prometheus"
          },
          "editorMode": "code",
          "exemplar": false,
          "expr": "sum by (namespace, pod) (\r\n    rate(container_fs_writes_bytes_total{\r\n        namespace=\"$ns\",\r\n        pod=~\"$pod\", \r\n        container!=\"POD\",\r\n        container!=\"\"\r\n    }\r\n    [$__rate_interval]\r\n    )\r\n)\r\n* on (namespace, pod) \r\n  group_left(label_service_name)\r\n    kube_pod_labels{\r\n      namespace=\"$ns\",\r\n      label_service_name=~\"$service_name\",\r\n      label_service_name=~\"$log_service_name\",\r\n      label_environment=~\"$env\",\r\n      pod=~\"$pod\"\r\n    }\r\n* -1",
          "format": "time_series",
          "hide": false,
          "instant": false,
          "legendFormat": "{{pod}} (write)",
          "range": true,
          "refId": "B"
        }
      ],
      "title": "Disk",
      "type": "timeseries"
    },
    {
      "datasource": {
        "type": "prometheus",
        "uid": "Prometheus"
      },
      "fieldConfig": {
        "defaults": {
          "color": {
            "mode": "palette-classic"
          },
          "custom": {
            "axisBorderShow": false,
            "axisCenteredZero": false,
            "axisColorMode": "text",
            "axisLabel": "",
            "axisPlacement": "auto",
            "barAlignment": 0,
            "barWidthFactor": 0.6,
            "drawStyle": "line",
            "fillOpacity": 0,
            "gradientMode": "none",
            "hideFrom": {
              "legend": false,
              "tooltip": false,
              "viz": false
            },
            "insertNulls": 60000,
            "lineInterpolation": "smooth",
            "lineStyle": {
              "fill": "solid"
            },
            "lineWidth": 1,
            "pointSize": 5,
            "scaleDistribution": {
              "type": "linear"
            },
            "showPoints": "auto",
            "showValues": false,
            "spanNulls": false,
            "stacking": {
              "group": "A",
              "mode": "none"
            },
            "thresholdsStyle": {
              "mode": "dashed"
            }
          },
          "fieldMinMax": false,
          "mappings": [],
          "max": 100,
          "min": 0,
          "thresholds": {
            "mode": "absolute",
            "steps": [
              {
                "color": "green",
                "value": 0
              },
              {
                "color": "red",
                "value": 100
              }
            ]
          },
          "unit": "percent"
        },
        "overrides": []
      },
      "gridPos": {
        "h": 6,
        "w": 7,
        "x": 0,
        "y": 17
      },
      "id": 14,
      "options": {
        "legend": {
          "calcs": [],
          "displayMode": "list",
          "placement": "bottom",
          "showLegend": true
        },
        "tooltip": {
          "hideZeros": false,
          "mode": "single",
          "sort": "none"
        }
      },
      "pluginVersion": "12.3.1",
      "targets": [
        {
          "datasource": {
            "type": "prometheus",
            "uid": "Prometheus"
          },
          "editorMode": "code",
          "exemplar": false,
          "expr": "100 *\r\n(\r\n  sum by (namespace, pod) (\r\n    rate(\r\n      container_cpu_usage_seconds_total{\r\n        namespace=\"$ns\",\r\n        pod=~\".*-sql.*\",\r\n        pod=~\"$pod\",\r\n        container!=\"\",\r\n        container!=\"POD\"\r\n      }[$__rate_interval]\r\n    )\r\n  )\r\n  /\r\n  on (namespace, pod)\r\n  group_left(label_service_name)\r\n  sum by (namespace, pod) (\r\n    kube_pod_container_resource_limits{\r\n      namespace=\"$ns\",\r\n      pod=~\".*-sql.*\",\r\n      pod=~\"$pod\",\r\n      resource=\"cpu\",\r\n      unit=\"core\"\r\n    }\r\n  )\r\n)\r\n* on (namespace, pod)\r\n  group_left(label_service_name)\r\n  kube_pod_labels{\r\n    namespace=\"$ns\",\r\n    pod=~\".*-sql.*\",\r\n    pod=~\"$pod\",\r\n    label_service_name=~\"$log_service_name\",\r\n    label_service_name=~\"$service_name\",\r\n    label_environment=~\"$env\"\r\n  }\r\n",
          "format": "time_series",
          "hide": false,
          "instant": false,
          "legendFormat": "{{pod}} ({{label_service_name}})",
          "range": true,
          "refId": "A"
        }
      ],
      "title": "DB CPU Utilization (%)",
      "type": "timeseries"
    },
    {
      "datasource": {
        "type": "prometheus",
        "uid": "Prometheus"
      },
      "fieldConfig": {
        "defaults": {
          "color": {
            "mode": "palette-classic"
          },
          "custom": {
            "axisBorderShow": false,
            "axisCenteredZero": false,
            "axisColorMode": "text",
            "axisLabel": "",
            "axisPlacement": "auto",
            "barAlignment": 0,
            "barWidthFactor": 0.6,
            "drawStyle": "line",
            "fillOpacity": 0,
            "gradientMode": "none",
            "hideFrom": {
              "legend": false,
              "tooltip": false,
              "viz": false
            },
            "insertNulls": 60000,
            "lineInterpolation": "smooth",
            "lineStyle": {
              "fill": "solid"
            },
            "lineWidth": 1,
            "pointSize": 5,
            "scaleDistribution": {
              "type": "linear"
            },
            "showPoints": "auto",
            "showValues": false,
            "spanNulls": false,
            "stacking": {
              "group": "A",
              "mode": "none"
            },
            "thresholdsStyle": {
              "mode": "dashed"
            }
          },
          "fieldMinMax": false,
          "mappings": [],
          "max": 100,
          "min": 0,
          "thresholds": {
            "mode": "absolute",
            "steps": [
              {
                "color": "green",
                "value": 0
              },
              {
                "color": "red",
                "value": 100
              }
            ]
          },
          "unit": "percent"
        },
        "overrides": []
      },
      "gridPos": {
        "h": 6,
        "w": 7,
        "x": 7,
        "y": 17
      },
      "id": 15,
      "options": {
        "legend": {
          "calcs": [],
          "displayMode": "list",
          "placement": "bottom",
          "showLegend": true
        },
        "tooltip": {
          "hideZeros": false,
          "mode": "single",
          "sort": "none"
        }
      },
      "pluginVersion": "12.3.1",
      "targets": [
        {
          "datasource": {
            "type": "prometheus",
            "uid": "Prometheus"
          },
          "editorMode": "code",
          "exemplar": false,
          "expr": "100 *\r\n(\r\n  sum by (namespace, pod) (\r\n    container_memory_working_set_bytes{\r\n      namespace=\"$ns\",\r\n      pod=~\".*-sql.*\",\r\n      container!=\"\",\r\n      container!=\"POD\"\r\n    }\r\n  )\r\n)\r\n/\r\nclamp_min(\r\n  sum by (namespace, pod) (\r\n    kube_pod_container_resource_limits{\r\n      namespace=\"$ns\",\r\n      pod=~\".*-sql.*\",\r\n      resource=\"memory\",\r\n      unit=\"byte\"\r\n    }\r\n  ),\r\n  1\r\n)\r\n* on(namespace, pod)\r\ngroup_left(label_service_name)\r\nkube_pod_labels{\r\n  namespace=\"$ns\",\r\n  pod=~\".*-sql.*\",\r\n  label_service_name=~\"$log_service_name\",\r\n  label_service_name=~\"$service_name\",\r\n  label_environment=~\"$env\"\r\n}\r\n",
          "format": "time_series",
          "hide": false,
          "instant": false,
          "legendFormat": "{{pod}} ({{label_service_name}})",
          "range": true,
          "refId": "A"
        }
      ],
      "title": "DB Memory Utilization (%)",
      "type": "timeseries"
    },
    {
      "datasource": {
        "type": "prometheus",
        "uid": "Prometheus"
      },
      "fieldConfig": {
        "defaults": {
          "color": {
            "mode": "palette-classic"
          },
          "custom": {
            "axisBorderShow": false,
            "axisCenteredZero": false,
            "axisColorMode": "text",
            "axisLabel": "",
            "axisPlacement": "auto",
            "barAlignment": 0,
            "barWidthFactor": 0.6,
            "drawStyle": "line",
            "fillOpacity": 0,
            "gradientMode": "none",
            "hideFrom": {
              "legend": false,
              "tooltip": false,
              "viz": false
            },
            "insertNulls": 60000,
            "lineInterpolation": "smooth",
            "lineStyle": {
              "fill": "solid"
            },
            "lineWidth": 1,
            "pointSize": 5,
            "scaleDistribution": {
              "type": "linear"
            },
            "showPoints": "auto",
            "showValues": false,
            "spanNulls": false,
            "stacking": {
              "group": "A",
              "mode": "none"
            },
            "thresholdsStyle": {
              "mode": "off"
            }
          },
          "fieldMinMax": false,
          "mappings": [],
          "min": 0,
          "thresholds": {
            "mode": "absolute",
            "steps": [
              {
                "color": "green",
                "value": 0
              },
              {
                "color": "red",
                "value": 0.8
              }
            ]
          },
          "unit": "ops/s"
        },
        "overrides": []
      },
      "gridPos": {
        "h": 6,
        "w": 5,
        "x": 14,
        "y": 17
      },
      "id": 11,
      "options": {
        "legend": {
          "calcs": [],
          "displayMode": "list",
          "placement": "bottom",
          "showLegend": true
        },
        "tooltip": {
          "hideZeros": false,
          "mode": "single",
          "sort": "none"
        }
      },
      "pluginVersion": "12.3.1",
      "targets": [
        {
          "datasource": {
            "type": "prometheus",
            "uid": "Prometheus"
          },
          "editorMode": "code",
          "exemplar": false,
          "expr": "sum by (service_name) (sqlserver_lock_wait_rate_per_second{service_name=~\"$service_name\", service_name=~\"$log_service_name\",deployment_environment=\"$env\"})",
          "format": "time_series",
          "hide": false,
          "instant": false,
          "legendFormat": "{{service_name}}",
          "range": true,
          "refId": "A"
        }
      ],
      "title": "SQL Lock Wait Rate",
      "type": "timeseries"
    },
    {
      "datasource": {
        "type": "prometheus",
        "uid": "Prometheus"
      },
      "fieldConfig": {
        "defaults": {
          "color": {
            "mode": "palette-classic"
          },
          "custom": {
            "axisBorderShow": false,
            "axisCenteredZero": false,
            "axisColorMode": "text",
            "axisLabel": "",
            "axisPlacement": "auto",
            "barAlignment": 0,
            "barWidthFactor": 0.6,
            "drawStyle": "line",
            "fillOpacity": 0,
            "gradientMode": "none",
            "hideFrom": {
              "legend": false,
              "tooltip": false,
              "viz": false
            },
            "insertNulls": 60000,
            "lineInterpolation": "smooth",
            "lineStyle": {
              "fill": "solid"
            },
            "lineWidth": 1,
            "pointSize": 5,
            "scaleDistribution": {
              "type": "linear"
            },
            "showPoints": "auto",
            "showValues": false,
            "spanNulls": false,
            "stacking": {
              "group": "A",
              "mode": "none"
            },
            "thresholdsStyle": {
              "mode": "off"
            }
          },
          "fieldMinMax": false,
          "mappings": [],
          "min": 0,
          "thresholds": {
            "mode": "absolute",
            "steps": [
              {
                "color": "green",
                "value": 0
              },
              {
                "color": "red",
                "value": 0.8
              }
            ]
          },
          "unit": "ops/s"
        },
        "overrides": []
      },
      "gridPos": {
        "h": 6,
        "w": 5,
        "x": 19,
        "y": 17
      },
      "id": 13,
      "options": {
        "legend": {
          "calcs": [],
          "displayMode": "list",
          "placement": "bottom",
          "showLegend": true
        },
        "tooltip": {
          "hideZeros": false,
          "mode": "single",
          "sort": "none"
        }
      },
      "pluginVersion": "12.3.1",
      "targets": [
        {
          "datasource": {
            "type": "prometheus",
            "uid": "Prometheus"
          },
          "editorMode": "code",
          "exemplar": false,
          "expr": "sum by (service_name) (sqlserver_deadlock_rate{service_name=~\"$service_name\", deployment_environment=\"$env\"})",
          "format": "time_series",
          "hide": false,
          "instant": false,
          "legendFormat": "{{service_name}} deadlocks/s",
          "range": true,
          "refId": "A"
        },
        {
          "datasource": {
            "type": "prometheus",
            "uid": "Prometheus"
          },
          "editorMode": "code",
          "exemplar": false,
          "expr": "sum by (service_name, wait_category) (rate(sqlserver_os_wait_duration{service_name=~\"$service_name\", deployment_environment=\"$env\"}[$__rate_interval]))",
          "format": "time_series",
          "hide": false,
          "instant": false,
          "legendFormat": "{{service_name}} {{wait_category}} wait s/s",
          "range": true,
          "refId": "B"
        }
      ],
      "title": "SQL Deadlocks / Waits",
      "type": "timeseries"
    },
    {
      "datasource": {
        "type": "loki",
        "uid": "Loki"
      },
      "fieldConfig": {
        "defaults": {
          "color": {
            "mode": "palette-classic"
          },
          "custom": {
            "axisBorderShow": false,
            "axisCenteredZero": false,
            "axisColorMode": "text",
            "axisLabel": "",
            "axisPlacement": "auto",
            "barAlignment": 0,
            "barWidthFactor": 0.8,
            "drawStyle": "bars",
            "fillOpacity": 100,
            "gradientMode": "none",
            "hideFrom": {
              "legend": false,
              "tooltip": false,
              "viz": false
            },
            "insertNulls": false,
            "lineInterpolation": "linear",
            "lineWidth": 0,
            "pointSize": 5,
            "scaleDistribution": {
              "type": "linear"
            },
            "showPoints": "never",
            "showValues": false,
            "spanNulls": false,
            "stacking": {
              "group": "A",
              "mode": "normal"
            },
            "thresholdsStyle": {
              "mode": "off"
            }
          },
          "mappings": [],
          "thresholds": {
            "mode": "absolute",
            "steps": [
              {
                "color": "green",
                "value": 0
              },
              {
                "color": "red",
                "value": 80
              }
            ]
          }
        },
        "overrides": [
          {
            "matcher": {
              "id": "byName",
              "options": "Error"
            },
            "properties": [
              {
                "id": "color",
                "value": {
                  "fixedColor": "semi-dark-red",
                  "mode": "fixed"
                }
              }
            ]
          },
          {
            "matcher": {
              "id": "byName",
              "options": "Information"
            },
            "properties": [
              {
                "id": "color",
                "value": {
                  "fixedColor": "blue",
                  "mode": "fixed"
                }
              }
            ]
          },
          {
            "matcher": {
              "id": "byName",
              "options": "Warning"
            },
            "properties": [
              {
                "id": "color",
                "value": {
                  "fixedColor": "light-orange",
                  "mode": "fixed"
                }
              }
            ]
          }
        ]
      },
      "gridPos": {
        "h": 6,
        "w": 24,
        "x": 0,
        "y": 23
      },
      "id": 1,
      "interval": "1m",
      "maxDataPoints": 200,
      "options": {
        "legend": {
          "calcs": [
            "sum"
          ],
          "displayMode": "list",
          "placement": "bottom",
          "showLegend": true
        },
        "tooltip": {
          "hideZeros": true,
          "mode": "multi",
          "sort": "asc"
        }
      },
      "pluginVersion": "12.3.1",
      "targets": [
        {
          "datasource": {
            "type": "loki",
            "uid": "Loki"
          },
          "direction": "backward",
          "editorMode": "code",
          "expr": "sum by (detected_level) (\r\n  count_over_time({service_name=~\"$service_name\", service_name!=\"unknown_service\", deployment_environment=\"$env\", k8s_pod_name=~\"$pod\"} | logfmt | detected_level!=\"\" [$__interval])\r\n)",
          "queryType": "range",
          "refId": "A"
        }
      ],
      "title": "Logs Timeline",
      "transformations": [
        {
          "id": "labelsToFields",
          "options": {
            "valueLabel": "detected_level"
          }
        },
        {
          "id": "joinByField",
          "options": {
            "byField": "Time",
            "mode": "outer"
          }
        },
        {
          "id": "organize",
          "options": {
            "excludeByName": {},
            "includeByName": {},
            "indexByName": {
              "Error": 1,
              "Information": 3,
              "Time": 0,
              "Warning": 2
            },
            "renameByName": {}
          },
          "topic": "series"
        }
      ],
      "type": "timeseries"
    },
    {
      "datasource": {
        "type": "loki",
        "uid": "Loki"
      },
      "fieldConfig": {
        "defaults": {},
        "overrides": [
          {
            "matcher": {
              "id": "byName",
              "options": "RequestPath"
            },
            "properties": []
          },
          {
            "matcher": {
              "id": "byName",
              "options": "service_name"
            },
            "properties": []
          },
          {
            "matcher": {
              "id": "byName",
              "options": "deployment_environment"
            },
            "properties": []
          },
          {
            "matcher": {
              "id": "byName",
              "options": "TraceId"
            },
            "properties": []
          }
        ]
      },
      "gridPos": {
        "h": 12,
        "w": 24,
        "x": 0,
        "y": 29
      },
      "id": 2,
      "options": {
        "dedupStrategy": "none",
        "detailsMode": "inline",
        "displayedFields": [
          "deployment_environment",
          "service_name",
          "RequestPath",
          "___LOG_LINE_BODY___"
        ],
        "enableInfiniteScrolling": true,
        "enableLogDetails": true,
        "prettifyLogMessage": true,
        "showControls": true,
        "showLabels": false,
        "showTime": true,
        "sortOrder": "Descending",
        "syntaxHighlighting": true,
        "wrapLogMessage": true
      },
      "pluginVersion": "12.3.1",
      "targets": [
        {
          "datasource": {
            "type": "loki",
            "uid": "Loki"
          },
          "direction": "backward",
          "editorMode": "code",
          "expr": "{service_name=~\"$service_name\", service_name!=\"unknown_service\", deployment_environment=\"$env\", k8s_pod_name=~\"$pod\"}\r\n| logfmt",
          "hide": false,
          "queryType": "range",
          "refId": "B"
        }
      ],
      "title": "Logs",
      "type": "logs"
    },
    {
      "datasource": {
        "type": "tempo",
        "uid": "Tempo"
      },
      "fieldConfig": {
        "defaults": {
          "color": {
            "mode": "thresholds"
          },
          "custom": {
            "align": "auto",
            "cellOptions": {
              "type": "auto"
            },
            "footer": {
              "reducers": []
            },
            "inspect": false
          },
          "mappings": [],
          "thresholds": {
            "mode": "absolute",
            "steps": [
              {
                "color": "green",
                "value": 0
              },
              {
                "color": "red",
                "value": 80
              }
            ]
          }
        },
        "overrides": []
      },
      "gridPos": {
        "h": 7,
        "w": 24,
        "x": 0,
        "y": 41
      },
      "id": 3,
      "options": {
        "cellHeight": "sm",
        "showHeader": true
      },
      "pluginVersion": "12.3.1",
      "targets": [
        {
          "datasource": {
            "type": "tempo",
            "uid": "Tempo"
          },
          "filters": [
            {
              "id": "96453b8c",
              "operator": "=",
              "scope": "span"
            }
          ],
          "limit": 200,
          "metricsQueryType": "range",
          "query": "{resource.service.name=~\"$service_name\" && resource.service.name!=\"unknown_service\" && resource.k8s.pod.name=~\"$pod\" && resource.deployment.environment=\"$env\"}",
          "queryType": "traceql",
          "refId": "A",
          "serviceMapUseNativeHistograms": false,
          "spss": 30,
          "tableType": "traces"
        }
      ],
      "title": "Traces",
      "type": "table"
    },
    {
      "collapsed": true,
      "gridPos": {
        "h": 1,
        "w": 24,
        "x": 0,
        "y": 48
      },
      "id": 17,
      "panels": [
        {
          "datasource": {
            "type": "prometheus",
            "uid": "Prometheus"
          },
          "fieldConfig": {
            "defaults": {
              "color": {
                "mode": "palette-classic"
              },
              "custom": {
                "axisBorderShow": false,
                "axisCenteredZero": false,
                "axisColorMode": "text",
                "axisLabel": "",
                "axisPlacement": "auto",
                "barAlignment": 0,
                "barWidthFactor": 0.6,
                "drawStyle": "line",
                "fillOpacity": 0,
                "gradientMode": "none",
                "hideFrom": {
                  "legend": false,
                  "tooltip": false,
                  "viz": false
                },
                "insertNulls": 60000,
                "lineInterpolation": "smooth",
                "lineStyle": {
                  "fill": "solid"
                },
                "lineWidth": 1,
                "pointSize": 5,
                "scaleDistribution": {
                  "type": "linear"
                },
                "showPoints": "auto",
                "showValues": false,
                "spanNulls": false,
                "stacking": {
                  "group": "A",
                  "mode": "none"
                },
                "thresholdsStyle": {
                  "mode": "off"
                }
              },
              "fieldMinMax": false,
              "mappings": [],
              "min": 0,
              "thresholds": {
                "mode": "absolute",
                "steps": [
                  {
                    "color": "green",
                    "value": 0
                  },
                  {
                    "color": "red",
                    "value": 0.8
                  }
                ]
              },
              "unit": "s"
            },
            "overrides": []
          },
          "gridPos": {
            "h": 6,
            "w": 5,
            "x": 0,
            "y": 55
          },
          "id": 12,
          "options": {
            "legend": {
              "calcs": [],
              "displayMode": "list",
              "placement": "bottom",
              "showLegend": true
            },
            "tooltip": {
              "hideZeros": false,
              "mode": "single",
              "sort": "none"
            }
          },
          "pluginVersion": "12.3.1",
          "targets": [
            {
              "datasource": {
                "type": "prometheus",
                "uid": "Prometheus"
              },
              "editorMode": "code",
              "exemplar": false,
              "expr": "avg by (service_name, performance_counter_object_name) (sqlserver_page_life_expectancy_seconds{service_name=~\"$service_name\", service_name=~\"$log_service_name\", deployment_environment=\"$env\"})",
              "format": "time_series",
              "hide": false,
              "instant": false,
              "legendFormat": "{{service_name}} ({{performance_counter_object_name}})",
              "range": true,
              "refId": "A"
            }
          ],
          "title": "SQL Page Life Expectancy",
          "type": "timeseries"
        },
        {
          "datasource": {
            "type": "prometheus",
            "uid": "Prometheus"
          },
          "fieldConfig": {
            "defaults": {
              "color": {
                "mode": "palette-classic"
              },
              "custom": {
                "axisBorderShow": false,
                "axisCenteredZero": false,
                "axisColorMode": "text",
                "axisLabel": "",
                "axisPlacement": "auto",
                "barAlignment": 0,
                "barWidthFactor": 0.6,
                "drawStyle": "line",
                "fillOpacity": 0,
                "gradientMode": "none",
                "hideFrom": {
                  "legend": false,
                  "tooltip": false,
                  "viz": false
                },
                "insertNulls": 60000,
                "lineInterpolation": "smooth",
                "lineStyle": {
                  "fill": "solid"
                },
                "lineWidth": 1,
                "pointSize": 5,
                "scaleDistribution": {
                  "type": "linear"
                },
                "showPoints": "auto",
                "showValues": false,
                "spanNulls": false,
                "stacking": {
                  "group": "A",
                  "mode": "none"
                },
                "thresholdsStyle": {
                  "mode": "off"
                }
              },
              "fieldMinMax": false,
              "mappings": [],
              "min": 0,
              "thresholds": {
                "mode": "absolute",
                "steps": [
                  {
                    "color": "green",
                    "value": 0
                  },
                  {
                    "color": "red",
                    "value": 0.8
                  }
                ]
              },
              "unit": "ops/s"
            },
            "overrides": []
          },
          "gridPos": {
            "h": 6,
            "w": 5,
            "x": 5,
            "y": 55
          },
          "id": 10,
          "options": {
            "legend": {
              "calcs": [],
              "displayMode": "list",
              "placement": "bottom",
              "showLegend": true
            },
            "tooltip": {
              "hideZeros": false,
              "mode": "single",
              "sort": "none"
            }
          },
          "pluginVersion": "12.3.1",
          "targets": [
            {
              "datasource": {
                "type": "prometheus",
                "uid": "Prometheus"
              },
              "editorMode": "code",
              "exemplar": false,
              "expr": "sum by (service_name) (sqlserver_batch_request_rate_per_second{service_name=~\"$service_name\", service_name=~\"$log_service_name\",deployment_environment=\"$env\"})",
              "format": "time_series",
              "hide": false,
              "instant": false,
              "legendFormat": "{{service_name}}",
              "range": true,
              "refId": "A"
            }
          ],
          "title": "SQL Batch Request Rate",
          "type": "timeseries"
        }
      ],
      "title": "Other",
      "type": "row"
    }
  ],
  "preload": false,
  "refresh": "5s",
  "schemaVersion": 42,
  "tags": [],
  "templating": {
    "list": [
      {
        "allValue": "^(unknown_service$)|(.+)",
        "current": {
          "text": "All",
          "value": [
            "$__all"
          ]
        },
        "datasource": {
          "type": "prometheus",
          "uid": "Prometheus"
        },
        "definition": "label_values(process_cpu_count{k8s_namespace_name=\"app-services\"},service_name)",
        "description": "",
        "includeAll": true,
        "label": "service_name",
        "multi": true,
        "name": "service_name",
        "options": [],
        "query": {
          "qryType": 1,
          "query": "label_values(process_cpu_count{k8s_namespace_name=\"app-services\"},service_name)",
          "refId": "PrometheusVariableQueryEditor-VariableQuery"
        },
        "refresh": 2,
        "regex": "^(?!unknown).*$",
        "type": "query"
      },
      {
        "allValue": ".+",
        "allowCustomValue": false,
        "current": {
          "text": "local",
          "value": "local"
        },
        "datasource": {
          "type": "prometheus",
          "uid": "Prometheus"
        },
        "definition": "label_values(process_cpu_count,deployment_environment)",
        "includeAll": false,
        "name": "env",
        "options": [],
        "query": {
          "qryType": 1,
          "query": "label_values(process_cpu_count,deployment_environment)",
          "refId": "PrometheusVariableQueryEditor-VariableQuery"
        },
        "refresh": 2,
        "regex": "",
        "type": "query"
      },
      {
        "current": {
          "text": "",
          "value": ""
        },
        "description": "",
        "label": "ts",
        "name": "ts",
        "options": [
          {
            "selected": true,
            "text": "",
            "value": ""
          }
        ],
        "query": "",
        "type": "textbox"
      },
      {
        "allValue": ".+",
        "current": {
          "text": "All",
          "value": [
            "$__all"
          ]
        },
        "datasource": {
          "type": "prometheus",
          "uid": "Prometheus"
        },
        "definition": "label_values(container_cpu_usage_seconds_total{namespace=\"app-services\"},pod)",
        "includeAll": true,
        "label": "pod",
        "multi": true,
        "name": "pod",
        "options": [],
        "query": {
          "qryType": 1,
          "query": "label_values(container_cpu_usage_seconds_total{namespace=\"app-services\"},pod)",
          "refId": "PrometheusVariableQueryEditor-VariableQuery"
        },
        "refresh": 2,
        "regex": "",
        "type": "query"
      },
      {
        "current": {
          "text": "app-services",
          "value": "app-services"
        },
        "hide": 2,
        "label": "ns",
        "name": "ns",
        "query": "app-services",
        "skipUrlSync": true,
        "type": "constant"
      },
      {
        "allValue": "^(unknown_service$)|(.+)",
        "current": {
          "text": "All",
          "value": "$__all"
        },
        "datasource": {
          "type": "prometheus",
          "uid": "Prometheus"
        },
        "definition": "label_values(kube_pod_labels{namespace=\"app-services\"},label_service_name)",
        "description": "",
        "includeAll": true,
        "label": "log_service_name",
        "name": "log_service_name",
        "options": [],
        "query": {
          "qryType": 1,
          "query": "label_values(kube_pod_labels{namespace=\"app-services\"},label_service_name)",
          "refId": "PrometheusVariableQueryEditor-VariableQuery"
        },
        "refresh": 2,
        "regex": "^(?!unknown).*$",
        "type": "query"
      }
    ]
  },
  "time": {
    "from": "now-5m",
    "to": "now"
  },
  "timepicker": {},
  "timezone": "browser",
  "title": "Logs/Traces2",
  "uid": "adzf64t2",
  "version": 48
}